s3_tool/.env.example
s3_tool/__init__.py
s3_tool/choices/access_types.py
s3_tool/choices/object_methods.py
s3_tool/main.py
s3_tool-0.3.6.dist-info/METADATA
s3_tool-0.3.6.dist-info/WHEEL
s3_tool-0.3.6.dist-info/entry_points.txt
s3_tool-0.3.6.dist-info/RECORD
