Metadata-Version: 2.1
Name: s3-tool
Version: 0.3.6
Summary: S3 CLI Tool to execute basic commands
Home-page: https://github.com/necromeo/s3-tool
License: MIT
Author: Ivan Andre Scheel
Author-email: andrescheel@protonmail.com
Requires-Python: >=3.11,<4.0
Classifier: License :: OSI Approved :: MIT License
Classifier: Programming Language :: Python :: 3
Classifier: Programming Language :: Python :: 3.11
Requires-Dist: boto3 (>=1.14.20,<2.0.0)
Requires-Dist: python-dotenv (>=1.0.0,<2.0.0)
Requires-Dist: tqdm (>=4.66.1,<5.0.0)
Requires-Dist: typer[all] (>=0.9.0,<0.10.0)
